mcp_server_yunxiao/__init__.py
mcp_server_yunxiao/client.py
mcp_server_yunxiao/tool_honeycomb.py
mcp_server_yunxiao/tools_beacon.py
mcp_server_yunxiao/tools_compass.py
mcp_server_yunxiao/tools_data360.py
mcp_server_yunxiao/tools_insight.py
mcp_server_yunxiao/tools_rubik.py
mcp_server_yunxiao/tools_spot.py
mcp_server_yunxiao/tools_weaver.py
mcp_server_yunxiao-0.1.21.dist-info/METADATA
mcp_server_yunxiao-0.1.21.dist-info/WHEEL
mcp_server_yunxiao-0.1.21.dist-info/entry_points.txt
mcp_server_yunxiao-0.1.21.dist-info/RECORD
