Metadata-Version: 2.4
Name: mcp-server-yunxiao
Version: 0.1.21
Summary: MCP Server for Yunxiao
Requires-Python: >=3.10
Requires-Dist: mcp[cli]>=1.0.0
Requires-Dist: requests>=2.31.0
